odoo/addons/product_route_mto/README.rst
odoo/addons/product_route_mto/__init__.py
odoo/addons/product_route_mto/__manifest__.py
odoo/addons/product_route_mto/i18n/es.po
odoo/addons/product_route_mto/i18n/fr_BE.po
odoo/addons/product_route_mto/i18n/it.po
odoo/addons/product_route_mto/i18n/product_route_mto.pot
odoo/addons/product_route_mto/models/__init__.py
odoo/addons/product_route_mto/models/product_template.py
odoo/addons/product_route_mto/readme/CONTRIBUTORS.rst
odoo/addons/product_route_mto/readme/DESCRIPTION.rst
odoo/addons/product_route_mto/static/description/icon.png
odoo/addons/product_route_mto/static/description/index.html
odoo/addons/product_route_mto/tests/__init__.py
odoo/addons/product_route_mto/tests/test_product_route_mto.py
odoo/addons/product_route_mto/views/product_template.xml
odoo14_addon_product_route_mto-14.0.1.0.1.dev3.dist-info/METADATA
odoo14_addon_product_route_mto-14.0.1.0.1.dev3.dist-info/WHEEL
odoo14_addon_product_route_mto-14.0.1.0.1.dev3.dist-info/top_level.txt
odoo14_addon_product_route_mto-14.0.1.0.1.dev3.dist-info/RECORD
